unused_attributes.py
unused_attributes-0.1.10.dist-info/LICENSE
unused_attributes-0.1.10.dist-info/METADATA
unused_attributes-0.1.10.dist-info/WHEEL
unused_attributes-0.1.10.dist-info/entry_points.txt
unused_attributes-0.1.10.dist-info/top_level.txt
unused_attributes-0.1.10.dist-info/RECORD
