Metadata-Version: 2.1
Name: unused-attributes
Version: 0.1.10
Summary: Find class unused attributes
Author-email: xor2003 <xor2003@gmx.com>
License: GPL
Project-URL: Homepage, https://github.com/xor2003/unused_attributes
Keywords: optimization,ununsed attributes,unused variables,runtime testing,code quality
Classifier: Development Status :: 4 - Beta
Classifier: Intended Audience :: Developers
Classifier: License :: OSI Approved :: GNU General Public License v3 or later (GPLv3+)
Classifier: Programming Language :: Python :: 3
Classifier: Programming Language :: Python :: 3.10
Classifier: Programming Language :: Python :: 3.11
Classifier: Programming Language :: Python :: 3.8
Classifier: Programming Language :: Python :: 3.9
Classifier: Operating System :: OS Independent
Classifier: Topic :: Software Development :: Quality Assurance
Requires-Python: >=3.8
License-File: LICENSE
